xhshow/__init__.py
xhshow/_version.py
xhshow/client.py
xhshow/py.typed
xhshow/session.py
xhshow/config/__init__.py
xhshow/config/config.py
xhshow/core/__init__.py
xhshow/core/common_sign.py
xhshow/core/crc32_encrypt.py
xhshow/core/crypto.py
xhshow/data/__init__.py
xhshow/data/fingerprint_data.py
xhshow/generators/__init__.py
xhshow/generators/fingerprint.py
xhshow/generators/fingerprint_helpers.py
xhshow/utils/__init__.py
xhshow/utils/bit_ops.py
xhshow/utils/encoder.py
xhshow/utils/hex_utils.py
xhshow/utils/random_gen.py
xhshow/utils/url_utils.py
xhshow/utils/validators.py
xhshow-0.1.8.dist-info/METADATA
xhshow-0.1.8.dist-info/WHEEL
xhshow-0.1.8.dist-info/licenses/LICENSE
xhshow-0.1.8.dist-info/RECORD
