Metadata-Version: 2.4
Name: xhshow
Version: 0.1.8
Summary: XHS API signature generator
Project-URL: Homepage, https://github.com/cloxl/xhshow
Project-URL: Repository, https://github.com/cloxl/xhshow
Project-URL: Issues, https://github.com/cloxl/xhshow/issues
Author-email: cloxl <cloxl@cloxl.com>
License-File: LICENSE
Classifier: Development Status :: 4 - Beta
Classifier: Intended Audience :: Developers
Classifier: License :: OSI Approved :: MIT License
Classifier: Programming Language :: Python :: 3
Classifier: Programming Language :: Python :: 3.10
Classifier: Programming Language :: Python :: 3.11
Classifier: Programming Language :: Python :: 3.12
Classifier: Topic :: Security :: Cryptography
Classifier: Typing :: Typed
Requires-Python: >=3.10
Requires-Dist: pycryptodome>=3.23.0
Provides-Extra: dev
Requires-Dist: black>=23.0.0; extra == 'dev'
Requires-Dist: pytest-asyncio>=0.21.0; extra == 'dev'
Requires-Dist: pytest>=7.0.0; extra == 'dev'
Requires-Dist: ruff>=0.1.0; extra == 'dev'
